twobody-0.8.3.dist-info/METADATA
twobody-0.8.3.dist-info/top_level.txt
twobody-0.8.3.dist-info/RECORD
twobody-0.8.3.dist-info/WHEEL
twobody-0.8.3.dist-info/LICENSE.rst
twobody/wrap.pxd
twobody/orbit.py
twobody/utils.py
twobody/reference_plane.py
twobody/barycenter.py
twobody/compiler_version.cpython-38-x86_64-linux-gnu.so
twobody/elements.py
twobody/bary_trends.py
twobody/transforms.py
twobody/wrap.pyx
twobody/conftest.py
twobody/_astropy_init.py
twobody/units.py
twobody/__init__.py
twobody/anomaly.py
twobody/version.py
twobody/setup_package.py
twobody/wrap.cpython-38-x86_64-linux-gnu.so
twobody/src/twobody.c
twobody/src/twobody.h
twobody/tests/test_transforms.py
twobody/tests/test_reference_plane.py
twobody/tests/test_orbit.py
twobody/tests/test_elements.py
twobody/tests/test_barycenter.py
twobody/tests/test_api.py
twobody/tests/test_anomaly.py
twobody/tests/test_bary_trends.py
twobody/tests/__init__.py
twobody/tests/setup_package.py
