Metadata-Version: 2.1
Name: twobody
Version: 0.8.3
Summary: The gravitational two-body problem.
Home-page: https://github.com/adrn/TwoBody
Author: Adrian Price-Whelan
Author-email: adrianmpw@gmail.com
License: MIT
Platform: UNKNOWN
Requires-Python: >=3.7
Provides-Extra: test
Provides-Extra: docs
License-File: licenses/LICENSE.rst
